{"name":null,"assets":"aoy4:pathy47:assets%2Fweek1%2Fimages%2Fweeb%2FbfPortrait.pngy4:sizei52129y4:typey5:IMAGEy2:idR1y7:preloadtgoR0y48:assets%2Fweek1%2Fimages%2Fweeb%2FinkPortrait.pngR2i76083R3R4R5R7R6tgoR0y64:assets%2Fweek1%2Fimages%2Fweeb%2FpixelUI%2FdialogueBox-pixel.pngR2i1039R3R4R5R8R6tgoR0y64:assets%2Fweek1%2Fimages%2Fweeb%2FpixelUI%2FdialogueBox-pixel.xmlR2i314R3y4:TEXTR5R9R6tgoR0y51:assets%2Fweek1%2Fimages%2Fweeb%2FsenpaiPortrait.pngR2i41216R3R4R5R11R6tgoR0y37:assets%2Fweek1%2Fweek1_stuff_here.txtR2zR3R10R5R12R6tgh","rootPath":"../","version":2,"libraryArgs":[],"libraryType":null}